pemmican/__init__.py
pemmican/cli.py
pemmican/const.py
pemmican/gui.py
pemmican/lang.py
pemmican/notify.py
pemmican/power.py
pemmican-1.0.3.dist-info/LICENSE.txt
pemmican-1.0.3.dist-info/METADATA
pemmican-1.0.3.dist-info/WHEEL
pemmican-1.0.3.dist-info/entry_points.txt
pemmican-1.0.3.dist-info/top_level.txt
pemmican-1.0.3.dist-info/RECORD
