Metadata-Version: 2.1
Name: pemmican
Version: 1.0.3
Summary: Notify users of Raspberry Pi 5 power issues
Author: Dave Jones
Author-email: dave.jones@canonical.com
Project-URL: Documentation, https://pemmican.readthedocs.io/
Project-URL: Source Code, https://github.com/waveform80/pemmican
Project-URL: Issue Tracker, https://github.com/waveform80/pemmican/issues
Keywords: raspberry pi pmic notify
Classifier: Development Status :: 4 - Beta
Classifier: Environment :: Console
Classifier: Intended Audience :: System Administrators
Classifier: License :: OSI Approved :: GNU General Public License v3 (GPLv3)
Classifier: Operating System :: POSIX :: Linux
Classifier: Programming Language :: Python
Classifier: Programming Language :: Python :: 3
Classifier: Programming Language :: Python :: 3.9
Classifier: Programming Language :: Python :: 3.10
Classifier: Programming Language :: Python :: 3.11
Classifier: Programming Language :: Python :: 3.12
Classifier: Topic :: System :: Boot
Requires-Python: >=3.9
License-File: LICENSE.txt
Requires-Dist: setuptools
Provides-Extra: doc
Requires-Dist: sphinx ; extra == 'doc'
Requires-Dist: sphinx-rtd-theme ; extra == 'doc'
Provides-Extra: gui
Requires-Dist: dbus-python ; extra == 'gui'
Requires-Dist: pyudev ; extra == 'gui'
Requires-Dist: pygobject ; extra == 'gui'
Provides-Extra: test
Requires-Dist: pytest ; extra == 'test'
Requires-Dist: pytest-cov ; extra == 'test'
